rigol_ds1000z/__init__.py
rigol_ds1000z/app/channel_tui.py
rigol_ds1000z/app/display_tui.py
rigol_ds1000z/app/shortcuts.py
rigol_ds1000z/app/tablecontrol_tui.py
rigol_ds1000z/app/timebase_tui.py
rigol_ds1000z/app/trigger_tui.py
rigol_ds1000z/app/tui.py
rigol_ds1000z/app/waveform_tui.py
rigol_ds1000z/cli.py
rigol_ds1000z/src/channel.py
rigol_ds1000z/src/display.py
rigol_ds1000z/src/ieee.py
rigol_ds1000z/src/oscope.py
rigol_ds1000z/src/timebase.py
rigol_ds1000z/src/trigger.py
rigol_ds1000z/src/waveform.py
rigol_ds1000z/utils.py
rigol_ds1000z-0.3.0.dist-info/entry_points.txt
rigol_ds1000z-0.3.0.dist-info/LICENSE
rigol_ds1000z-0.3.0.dist-info/WHEEL
rigol_ds1000z-0.3.0.dist-info/METADATA
rigol_ds1000z-0.3.0.dist-info/RECORD
