Metadata-Version: 2.1
Name: rigol-ds1000z
Version: 0.3.0
Summary: Python library for interfacing with Rigol DS1000Z series oscilloscopes.
Home-page: https://amosborne.github.io/rigol-ds1000z/
License: MIT
Author: amosborne
Author-email: amosborne@users.noreply.github.com
Requires-Python: >=3.9,<4.0
Classifier: License :: OSI Approved :: MIT License
Classifier: Programming Language :: Python :: 3
Classifier: Programming Language :: Python :: 3.10
Classifier: Programming Language :: Python :: 3.9
Classifier: Topic :: System :: Hardware :: Hardware Drivers
Requires-Dist: PyVISA (>=1.11.3,<2.0.0)
Requires-Dist: PyVISA-py (>=0.5.3,<0.6.0)
Requires-Dist: matplotlib (>=3.5.1,<4.0.0)
Requires-Dist: numpy (>=1.22.2,<2.0.0)
Requires-Dist: pyserial (>=3.5,<4.0)
Requires-Dist: pyusb (>=1.2.1,<2.0.0)
Requires-Dist: si-prefix (>=1.2.2,<2.0.0)
Requires-Dist: textual (>=0.1.18,<0.2.0)
Project-URL: Repository, https://github.com/amosborne/rigol-ds1000z
